funcy-stubs/__init__.pyi
funcy-stubs/_inspect.pyi
funcy-stubs/calc.pyi
funcy-stubs/colls.pyi
funcy-stubs/compat.pyi
funcy-stubs/debug.pyi
funcy-stubs/decorators.pyi
funcy-stubs/flow.pyi
funcy-stubs/funcmakers.pyi
funcy-stubs/funcolls.pyi
funcy-stubs/funcs.pyi
funcy-stubs/objects.pyi
funcy-stubs/primitives.pyi
funcy-stubs/py2.pyi
funcy-stubs/py3.pyi
funcy-stubs/seqs.pyi
funcy-stubs/strings.pyi
funcy-stubs/tree.pyi
funcy-stubs/types.pyi
funcy_stubs-0.1.1.dist-info/WHEEL
funcy_stubs-0.1.1.dist-info/METADATA
funcy_stubs-0.1.1.dist-info/license_files/LICENSE
funcy_stubs-0.1.1.dist-info/RECORD
