Metadata-Version: 2.1
Name: funcy-stubs
Version: 0.1.1
Summary: Type stubs for funcy
License: BSD
Keywords: type-annotations,mypy-stubs
Author-email: Ruan Comelli <ruancomelli@gmail.com>
Requires-Python: >=3.7
Classifier: Intended Audience :: Developers
Classifier: License :: OSI Approved :: BSD License
Classifier: Programming Language :: Python
Classifier: Programming Language :: Python :: 3
Classifier: Programming Language :: Python :: 3.10
Classifier: Programming Language :: Python :: 3.7
Classifier: Programming Language :: Python :: 3.8
Classifier: Programming Language :: Python :: 3.9
Classifier: Topic :: Software Development :: Libraries :: Python Modules
Classifier: Typing :: Stubs Only
Requires-Dist: funcy==1.17
Requires-Dist: typing-extensions>=3.10.0
Project-URL: Documentation, https://github.com/ruancomelli/funcy-stubs
Project-URL: Homepage, https://github.com/ruancomelli/funcy-stubs
Project-URL: Repository, https://github.com/ruancomelli/funcy-stubs
